{
  "scope": "combined",
  "by": "protocol",
  "count": 3,
  "allocation": [
    {
      "protocol": "marinade",
      "protocol_label": "Marinade",
      "protocols": [
        "marinade_native"
      ],
      "total_usd": 16015.172166483204
    },
    {
      "protocol": "holdings",
      "protocol_label": "Holdings",
      "protocols": [
        "wallet_tokens"
      ],
      "total_usd": 12305.808859149633
    },
    {
      "protocol": "raydium",
      "protocol_label": "Raydium",
      "protocols": [
        "raydium"
      ],
      "total_usd": 4494.780417658816
    }
  ]
}
